setup.py
django_icecat.egg-info/PKG-INFO
django_icecat.egg-info/SOURCES.txt
django_icecat.egg-info/dependency_links.txt
django_icecat.egg-info/top_level.txt
icecat/__init__.py
icecat/models.py
icecat/settings.py
icecat/management/__init__.py
icecat/management/commands/__init__.py
icecat/management/commands/import_categories.py
icecat/management/commands/import_products.py
icecat/management/commands/import_suppliers.py
icecat/migrations/0001_initial.py
icecat/migrations/0002_auto__add_category__del_field_product_name__add_field_product_model_na.py
icecat/migrations/0003_auto__add_field_product_category.py
icecat/migrations/0004_auto__del_field_product_updated__del_field_product_date_added__add_fie.py
icecat/migrations/0005_auto__add_field_product_part.py
icecat/migrations/0006_auto__add_field_product_thumbnail.py
icecat/migrations/0007_auto__add_field_product_on_market.py
icecat/migrations/__init__.py