Metadata-Version: 1.0
Name: django-icecat
Version: 0.1.1
Summary: Django models and tools for easy icecat importing
Home-page: http://github.com/svdgraaf/django-icecat/
Author: Sander van de Graaf
Author-email: mail@svdgraaf.nl
License: UNKNOWN
Platform: UNKNOWN
Classifier: Development Status :: 4 - Beta
Classifier: Intended Audience :: Developers
Classifier: Framework :: Django
Classifier: License :: OSI Approved :: GNU General Public License v3 (GPLv3)
Classifier: Natural Language :: English
Classifier: Operating System :: OS Independent
Classifier: Programming Language :: Python
Classifier: Topic :: Software Development :: Libraries :: Python Modules
Classifier: Environment :: Web Environment
